graham/__init__.py
graham/core.py
graham/fields.py
graham/utils.py
graham/tests/__init__.py
graham/tests/test_core.py
graham/tests/test_fields.py
graham/tests/test_overall.py
graham-0.1.11.dist-info/METADATA
graham-0.1.11.dist-info/WHEEL
graham-0.1.11.dist-info/entry_points.txt
graham-0.1.11.dist-info/top_level.txt
graham-0.1.11.dist-info/RECORD
